{
    "size": 20, 
    "vtable": [], 
    "members": [
        {
            "offset": 0, 
            "type": "int", 
            "size": 4, 
            "name": "list_size"
        }, 
        {
            "offset": 4, 
            "type": "int", 
            "size": 4, 
            "name": "num_active"
        }, 
        {
            "offset": 8, 
            "type": "int", 
            "size": 4, 
            "name": "new_count"
        }, 
        {
            "offset": 12, 
            "type": "int", 
            "size": 4, 
            "name": "collapse_list"
        }, 
        {
            "offset": 16, 
            "type": "RGE_Tile_List_Node *", 
            "size": 4, 
            "name": "list"
        }
    ], 
    "name": "RGE_Tile_List"
}