{
    "size": 596, 
    "vtable": [], 
    "members": [
        {
            "offset": 0, 
            "type": "int", 
            "size": 4, 
            "name": "custom_draw"
        }, 
        {
            "offset": 4, 
            "type": "TDrawArea *", 
            "size": 4, 
            "name": "render_area"
        }, 
        {
            "offset": 8, 
            "type": "TDrawArea *", 
            "size": 4, 
            "name": "save_area"
        }, 
        {
            "offset": 12, 
            "type": "TDrawArea *", 
            "size": 4, 
            "name": "primary_area"
        }, 
        {
            "offset": 16, 
            "type": "int", 
            "size": 4, 
            "name": "Num_Cursors"
        }, 
        {
            "offset": 20, 
            "type": "int", 
            "size": 4, 
            "name": "Max_Cursors"
        }, 
        {
            "offset": 24, 
            "type": "TDrawArea *[16]", 
            "size": 64, 
            "name": "cursors"
        }, 
        {
            "offset": 88, 
            "type": "TShape *", 
            "size": 4, 
            "name": "Cursor_Shape"
        }, 
        {
            "offset": 92, 
            "type": "int", 
            "size": 4, 
            "name": "Mouse_Mode"
        }, 
        {
            "offset": 96, 
            "type": "int", 
            "size": 4, 
            "name": "Max_CX"
        }, 
        {
            "offset": 100, 
            "type": "int", 
            "size": 4, 
            "name": "Max_CY"
        }, 
        {
            "offset": 104, 
            "type": "int", 
            "size": 4, 
            "name": "cWidth"
        }, 
        {
            "offset": 108, 
            "type": "int", 
            "size": 4, 
            "name": "cHeight"
        }, 
        {
            "offset": 112, 
            "type": "int", 
            "size": 4, 
            "name": "gWidth"
        }, 
        {
            "offset": 116, 
            "type": "int", 
            "size": 4, 
            "name": "gHeight"
        }, 
        {
            "offset": 120, 
            "type": "long", 
            "size": 4, 
            "name": "mouse_x"
        }, 
        {
            "offset": 124, 
            "type": "long", 
            "size": 4, 
            "name": "mouse_y"
        }, 
        {
            "offset": 128, 
            "type": "long", 
            "size": 4, 
            "name": "save_x"
        }, 
        {
            "offset": 132, 
            "type": "long", 
            "size": 4, 
            "name": "save_y"
        }, 
        {
            "offset": 136, 
            "type": "int", 
            "size": 4, 
            "name": "facet"
        }, 
        {
            "offset": 140, 
            "type": "int", 
            "size": 4, 
            "name": "game_facet"
        }, 
        {
            "offset": 144, 
            "type": "int", 
            "size": 4, 
            "name": "next_facet"
        }, 
        {
            "offset": 148, 
            "type": "int", 
            "size": 4, 
            "name": "last_facet"
        }, 
        {
            "offset": 152, 
            "type": "int", 
            "size": 4, 
            "name": "d_top"
        }, 
        {
            "offset": 156, 
            "type": "int", 
            "size": 4, 
            "name": "d_left"
        }, 
        {
            "offset": 160, 
            "type": "int", 
            "size": 4, 
            "name": "d_bottom"
        }, 
        {
            "offset": 164, 
            "type": "int", 
            "size": 4, 
            "name": "d_right"
        }, 
        {
            "offset": 168, 
            "type": "int", 
            "size": 4, 
            "name": "g_top"
        }, 
        {
            "offset": 172, 
            "type": "int", 
            "size": 4, 
            "name": "g_left"
        }, 
        {
            "offset": 176, 
            "type": "int", 
            "size": 4, 
            "name": "g_bottom"
        }, 
        {
            "offset": 180, 
            "type": "int", 
            "size": 4, 
            "name": "g_right"
        }, 
        {
            "offset": 184, 
            "type": "int", 
            "size": 4, 
            "name": "save_area_valid"
        }, 
        {
            "offset": 188, 
            "type": "tagRECT", 
            "size": 16, 
            "name": "save_rect"
        }, 
        {
            "offset": 204, 
            "type": "tagRECT", 
            "size": 16, 
            "name": "mouse_rect"
        }, 
        {
            "offset": 220, 
            "type": "tagRECT", 
            "size": 16, 
            "name": "cursor_rect"
        }, 
        {
            "offset": 236, 
            "type": "tagRECT", 
            "size": 16, 
            "name": "new_save_rect"
        }, 
        {
            "offset": 252, 
            "type": "tagRECT", 
            "size": 16, 
            "name": "restore_rect"
        }, 
        {
            "offset": 268, 
            "type": "tagRECT", 
            "size": 16, 
            "name": "game_window"
        }, 
        {
            "offset": 284, 
            "type": "IDirectDrawSurface *", 
            "size": 4, 
            "name": "restoreSurface"
        }, 
        {
            "offset": 288, 
            "type": "IDirectDrawSurface *", 
            "size": 4, 
            "name": "renderSurface"
        }, 
        {
            "offset": 292, 
            "type": "IDirectDrawSurface *", 
            "size": 4, 
            "name": "PrimarySurface"
        }, 
        {
            "offset": 296, 
            "type": "int", 
            "size": 4, 
            "name": "active"
        }, 
        {
            "offset": 300, 
            "type": "int", 
            "size": 4, 
            "name": "drawn"
        }, 
        {
            "offset": 304, 
            "type": "int", 
            "size": 4, 
            "name": "Shutdown"
        }, 
        {
            "offset": 308, 
            "type": "int", 
            "size": 4, 
            "name": "Setup"
        }, 
        {
            "offset": 312, 
            "type": "int", 
            "size": 4, 
            "name": "GameMode"
        }, 
        {
            "offset": 316, 
            "type": "int", 
            "size": 4, 
            "name": "GameEnabled"
        }, 
        {
            "offset": 320, 
            "type": "int", 
            "size": 4, 
            "name": "MouseOnScreen"
        }, 
        {
            "offset": 324, 
            "type": "ulong", 
            "size": 4, 
            "name": "LastDrawTime"
        }, 
        {
            "offset": 328, 
            "type": "long", 
            "size": 4, 
            "name": "LastddError"
        }, 
        {
            "offset": 332, 
            "type": "char[260]", 
            "size": 260, 
            "name": "cursor_file"
        }, 
        {
            "offset": 592, 
            "type": "int", 
            "size": 4, 
            "name": "cursor_file_id"
        }
    ], 
    "name": "TMousePointer"
}